classic/db_utils/__init__.py
classic/db_utils/exceptions.py
classic/db_utils/pool.py
classic/db_utils/poolvalidators.py
classic/db_utils/scoped_connection.py
classic/db_utils/types.py
classic_db_utils-2.2.3.dist-info/licenses/LICENSE.txt
classic_db_utils-2.2.3.dist-info/METADATA
classic_db_utils-2.2.3.dist-info/WHEEL
classic_db_utils-2.2.3.dist-info/top_level.txt
classic_db_utils-2.2.3.dist-info/RECORD
