Metadata-Version: 2.4
Name: classic-db-utils
Version: 2.2.3
Summary: Набор утилит для обегчения создания композитов
Author-email: Sergey Variasov <variasov@gmail.com>
License-Expression: MIT
Requires-Python: >=3.10
License-File: LICENSE.txt
Provides-Extra: dev
Requires-Dist: pytest~=7.4; extra == "dev"
Requires-Dist: pymssql~=2.3; extra == "dev"
Requires-Dist: build~=1.2.2.post1; extra == "dev"
Requires-Dist: pytest~=8.3; extra == "dev"
Requires-Dist: pytest-cov~=6.0; extra == "dev"
Requires-Dist: twine~=4.0; extra == "dev"
Dynamic: license-file
